[
  {
    "id": 100,
    "nom": "Nelle",
    "prenom": "Garbe",
    "email": "Nelle.Garbe@btst.com",
    "poste": "Manager"
  },
  {
    "id": 101,
    "nom": "Vonny",
    "prenom": "Fadiman",
    "email": "Vonny.Fadiman@btst.com",
    "poste": "Lead Dev"
  },
  {
    "id": 102,
    "nom": "Aaren",
    "prenom": "Love",
    "email": "Aaren.Love@btst.com",
    "poste": "Manager"
  },
  {
    "id": 103,
    "nom": "Marleah",
    "prenom": "Scammon",
    "email": "Marleah.Scammon@btst.com",
    "poste": "Manager"
  },
  {
    "id": 104,
    "nom": "Philis",
    "prenom": "Latini",
    "email": "Philis.Latini@btst.com",
    "poste": "Alternant"
  },
  {
    "id": 105,
    "nom": "Aurore",
    "prenom": "Leary",
    "email": "Aurore.Leary@btst.com",
    "poste": "Alternant"
  },
  {
    "id": 106,
    "nom": "Desirae",
    "prenom": "Monaco",
    "email": "Desirae.Monaco@btst.com",
    "poste": "Alternant"
  },
  {
    "id": 107,
    "nom": "Tatiania",
    "prenom": "Edmund",
    "email": "Tatiania.Edmund@btst.com",
    "poste": "Alternant"
  },
  {
    "id": 108,
    "nom": "Jackie",
    "prenom": "Brady",
    "email": "Jackie.Brady@btst.com",
    "poste": "Lead Dev"
  },
  {
    "id": 109,
    "nom": "Teriann",
    "prenom": "Chobot",
    "email": "Teriann.Chobot@btst.com",
    "poste": "Alternant"
  },
  {
    "id": 110,
    "nom": "Raf",
    "prenom": "Tarrant",
    "email": "Raf.Tarrant@btst.com",
    "poste": "Manager"
  },
  {
    "id": 111,
    "nom": "Danny",
    "prenom": "Anastatius",
    "email": "Danny.Anastatius@btst.com",
    "poste": "Manager"
  },
  {
    "id": 112,
    "nom": "Monika",
    "prenom": "Linskey",
    "email": "Monika.Linskey@btst.com",
    "poste": "Alternant"
  },
  {
    "id": 113,
    "nom": "Lindie",
    "prenom": "Pascia",
    "email": "Lindie.Pascia@btst.com",
    "poste": "Alternant"
  },
  {
    "id": 114,
    "nom": "Alyssa",
    "prenom": "Alwin",
    "email": "Alyssa.Alwin@btst.com",
    "poste": "Alternant"
  },
  {
    "id": 115,
    "nom": "Roz",
    "prenom": "Krystle",
    "email": "Roz.Krystle@btst.com",
    "poste": "Alternant"
  },
  {
    "id": 116,
    "nom": "Lucy",
    "prenom": "Yerkovich",
    "email": "Lucy.Yerkovich@btst.com",
    "poste": "Lead Dev"
  },
  {
    "id": 117,
    "nom": "Cassandra",
    "prenom": "Allina",
    "email": "Cassandra.Allina@btst.com",
    "poste": "Dev"
  },
  {
    "id": 118,
    "nom": "Di",
    "prenom": "Eachern",
    "email": "Di.Eachern@btst.com",
    "poste": "Manager"
  },
  {
    "id": 119,
    "nom": "Alisha",
    "prenom": "Swigart",
    "email": "Alisha.Swigart@btst.com",
    "poste": "Dev"
  },
  {
    "id": 120,
    "nom": "Randa",
    "prenom": "Wittie",
    "email": "Randa.Wittie@btst.com",
    "poste": "Manager"
  },
  {
    "id": 121,
    "nom": "Jsandye",
    "prenom": "Haerr",
    "email": "Jsandye.Haerr@btst.com",
    "poste": "Lead Dev"
  },
  {
    "id": 122,
    "nom": "Rebeca",
    "prenom": "Kirbee",
    "email": "Rebeca.Kirbee@btst.com",
    "poste": "Alternant"
  },
  {
    "id": 123,
    "nom": "Queenie",
    "prenom": "Garrison",
    "email": "Queenie.Garrison@btst.com",
    "poste": "Alternant"
  },
  {
    "id": 124,
    "nom": "Maridel",
    "prenom": "Charity",
    "email": "Maridel.Charity@btst.com",
    "poste": "Lead Dev"
  },
  {
    "id": 125,
    "nom": "Alameda",
    "prenom": "Helve",
    "email": "Alameda.Helve@btst.com",
    "poste": "Manager"
  },
  {
    "id": 126,
    "nom": "Rochette",
    "prenom": "Wattenberg",
    "email": "Rochette.Wattenberg@btst.com",
    "poste": "Alternant"
  },
  {
    "id": 127,
    "nom": "Amara",
    "prenom": "Raama",
    "email": "Amara.Raama@btst.com",
    "poste": "Manager"
  },
  {
    "id": 128,
    "nom": "Aubrie",
    "prenom": "Stelle",
    "email": "Aubrie.Stelle@btst.com",
    "poste": "Lead Dev"
  },
  {
    "id": 129,
    "nom": "Angelique",
    "prenom": "Duwalt",
    "email": "Angelique.Duwalt@btst.com",
    "poste": "Dev"
  },
  {
    "id": 130,
    "nom": "Tressa",
    "prenom": "Ilka",
    "email": "Tressa.Ilka@btst.com",
    "poste": "Lead Dev"
  },
  {
    "id": 131,
    "nom": "Caressa",
    "prenom": "Kauppi",
    "email": "Caressa.Kauppi@btst.com",
    "poste": "Lead Dev"
  },
  {
    "id": 132,
    "nom": "Chrystel",
    "prenom": "Peti",
    "email": "Chrystel.Peti@btst.com",
    "poste": "Manager"
  },
  {
    "id": 133,
    "nom": "Netty",
    "prenom": "Grayce",
    "email": "Netty.Grayce@btst.com",
    "poste": "Dev"
  },
  {
    "id": 134,
    "nom": "Robinia",
    "prenom": "Madox",
    "email": "Robinia.Madox@btst.com",
    "poste": "Lead Dev"
  },
  {
    "id": 135,
    "nom": "Kirstin",
    "prenom": "Elephus",
    "email": "Kirstin.Elephus@btst.com",
    "poste": "Dev"
  },
  {
    "id": 136,
    "nom": "Marita",
    "prenom": "Isidore",
    "email": "Marita.Isidore@btst.com",
    "poste": "Lead Dev"
  },
  {
    "id": 137,
    "nom": "Maud",
    "prenom": "Krystle",
    "email": "Maud.Krystle@btst.com",
    "poste": "Lead Dev"
  },
  {
    "id": 138,
    "nom": "Concettina",
    "prenom": "McCutcheon",
    "email": "Concettina.McCutcheon@btst.com",
    "poste": "Alternant"
  },
  {
    "id": 139,
    "nom": "Katleen",
    "prenom": "Pulsifer",
    "email": "Katleen.Pulsifer@btst.com",
    "poste": "Alternant"
  },
  {
    "id": 140,
    "nom": "Jackie",
    "prenom": "Melan",
    "email": "Jackie.Melan@btst.com",
    "poste": "Manager"
  },
  {
    "id": 141,
    "nom": "Ariela",
    "prenom": "Charmine",
    "email": "Ariela.Charmine@btst.com",
    "poste": "Alternant"
  },
  {
    "id": 142,
    "nom": "Natka",
    "prenom": "Rocray",
    "email": "Natka.Rocray@btst.com",
    "poste": "Lead Dev"
  },
  {
    "id": 143,
    "nom": "Sheree",
    "prenom": "Fry",
    "email": "Sheree.Fry@btst.com",
    "poste": "Lead Dev"
  },
  {
    "id": 144,
    "nom": "Merry",
    "prenom": "Moina",
    "email": "Merry.Moina@btst.com",
    "poste": "Alternant"
  },
  {
    "id": 145,
    "nom": "Marylou",
    "prenom": "My",
    "email": "Marylou.My@btst.com",
    "poste": "Manager"
  },
  {
    "id": 146,
    "nom": "Claresta",
    "prenom": "Sholley",
    "email": "Claresta.Sholley@btst.com",
    "poste": "Dev"
  },
  {
    "id": 147,
    "nom": "Clarice",
    "prenom": "Kress",
    "email": "Clarice.Kress@btst.com",
    "poste": "Manager"
  },
  {
    "id": 148,
    "nom": "Adele",
    "prenom": "Alfons",
    "email": "Adele.Alfons@btst.com",
    "poste": "Manager"
  },
  {
    "id": 149,
    "nom": "Shannah",
    "prenom": "Marlie",
    "email": "Shannah.Marlie@btst.com",
    "poste": "Dev"
  },
  {
    "id": 150,
    "nom": "Blinni",
    "prenom": "Erskine",
    "email": "Blinni.Erskine@btst.com",
    "poste": "Alternant"
  },
  {
    "id": 151,
    "nom": "Linet",
    "prenom": "Frodi",
    "email": "Linet.Frodi@btst.com",
    "poste": "Dev"
  },
  {
    "id": 152,
    "nom": "Kellen",
    "prenom": "Buckler",
    "email": "Kellen.Buckler@btst.com",
    "poste": "Manager"
  },
  {
    "id": 153,
    "nom": "Max",
    "prenom": "Shanley",
    "email": "Max.Shanley@btst.com",
    "poste": "Lead Dev"
  },
  {
    "id": 154,
    "nom": "Marcy",
    "prenom": "Larochelle",
    "email": "Marcy.Larochelle@btst.com",
    "poste": "Alternant"
  },
  {
    "id": 155,
    "nom": "Marnia",
    "prenom": "Cadmar",
    "email": "Marnia.Cadmar@btst.com",
    "poste": "Manager"
  },
  {
    "id": 156,
    "nom": "June",
    "prenom": "Byrne",
    "email": "June.Byrne@btst.com",
    "poste": "Alternant"
  },
  {
    "id": 157,
    "nom": "Carolina",
    "prenom": "Gregrory",
    "email": "Carolina.Gregrory@btst.com",
    "poste": "Alternant"
  },
  {
    "id": 158,
    "nom": "Melodie",
    "prenom": "Destinee",
    "email": "Melodie.Destinee@btst.com",
    "poste": "Manager"
  },
  {
    "id": 159,
    "nom": "Karlee",
    "prenom": "Alfons",
    "email": "Karlee.Alfons@btst.com",
    "poste": "Alternant"
  },
  {
    "id": 160,
    "nom": "Minne",
    "prenom": "Tremayne",
    "email": "Minne.Tremayne@btst.com",
    "poste": "Dev"
  },
  {
    "id": 161,
    "nom": "Peri",
    "prenom": "Kevon",
    "email": "Peri.Kevon@btst.com",
    "poste": "Lead Dev"
  },
  {
    "id": 162,
    "nom": "Tomasina",
    "prenom": "Maisey",
    "email": "Tomasina.Maisey@btst.com",
    "poste": "Alternant"
  },
  {
    "id": 163,
    "nom": "Arlena",
    "prenom": "Gale",
    "email": "Arlena.Gale@btst.com",
    "poste": "Alternant"
  },
  {
    "id": 164,
    "nom": "Mureil",
    "prenom": "Dowski",
    "email": "Mureil.Dowski@btst.com",
    "poste": "Dev"
  },
  {
    "id": 165,
    "nom": "Harmonia",
    "prenom": "Eliathas",
    "email": "Harmonia.Eliathas@btst.com",
    "poste": "Manager"
  },
  {
    "id": 166,
    "nom": "Aryn",
    "prenom": "Fillbert",
    "email": "Aryn.Fillbert@btst.com",
    "poste": "Dev"
  },
  {
    "id": 167,
    "nom": "Merci",
    "prenom": "Andrel",
    "email": "Merci.Andrel@btst.com",
    "poste": "Alternant"
  },
  {
    "id": 168,
    "nom": "Moyna",
    "prenom": "Latini",
    "email": "Moyna.Latini@btst.com",
    "poste": "Lead Dev"
  },
  {
    "id": 169,
    "nom": "Arabel",
    "prenom": "Blisse",
    "email": "Arabel.Blisse@btst.com",
    "poste": "Manager"
  },
  {
    "id": 170,
    "nom": "Aubrie",
    "prenom": "Ursulette",
    "email": "Aubrie.Ursulette@btst.com",
    "poste": "Alternant"
  },
  {
    "id": 171,
    "nom": "Nickie",
    "prenom": "Kravits",
    "email": "Nickie.Kravits@btst.com",
    "poste": "Lead Dev"
  },
  {
    "id": 172,
    "nom": "Robbi",
    "prenom": "Bettine",
    "email": "Robbi.Bettine@btst.com",
    "poste": "Lead Dev"
  },
  {
    "id": 173,
    "nom": "Candy",
    "prenom": "Suzetta",
    "email": "Candy.Suzetta@btst.com",
    "poste": "Lead Dev"
  },
  {
    "id": 174,
    "nom": "Daune",
    "prenom": "Meli",
    "email": "Daune.Meli@btst.com",
    "poste": "Manager"
  },
  {
    "id": 175,
    "nom": "Gianina",
    "prenom": "Carbo",
    "email": "Gianina.Carbo@btst.com",
    "poste": "Manager"
  },
  {
    "id": 176,
    "nom": "Jenda",
    "prenom": "Peti",
    "email": "Jenda.Peti@btst.com",
    "poste": "Dev"
  },
  {
    "id": 177,
    "nom": "Randa",
    "prenom": "Lowry",
    "email": "Randa.Lowry@btst.com",
    "poste": "Lead Dev"
  },
  {
    "id": 178,
    "nom": "Jolyn",
    "prenom": "Maroney",
    "email": "Jolyn.Maroney@btst.com",
    "poste": "Lead Dev"
  },
  {
    "id": 179,
    "nom": "Candi",
    "prenom": "Fredi",
    "email": "Candi.Fredi@btst.com",
    "poste": "Lead Dev"
  },
  {
    "id": 180,
    "nom": "Konstance",
    "prenom": "Stevy",
    "email": "Konstance.Stevy@btst.com",
    "poste": "Alternant"
  },
  {
    "id": 181,
    "nom": "Letizia",
    "prenom": "Anselmi",
    "email": "Letizia.Anselmi@btst.com",
    "poste": "Manager"
  },
  {
    "id": 182,
    "nom": "Allyce",
    "prenom": "Thilda",
    "email": "Allyce.Thilda@btst.com",
    "poste": "Lead Dev"
  },
  {
    "id": 183,
    "nom": "Viviene",
    "prenom": "Magdalen",
    "email": "Viviene.Magdalen@btst.com",
    "poste": "Manager"
  },
  {
    "id": 184,
    "nom": "Paulita",
    "prenom": "Merell",
    "email": "Paulita.Merell@btst.com",
    "poste": "Lead Dev"
  },
  {
    "id": 185,
    "nom": "Catharine",
    "prenom": "Alejoa",
    "email": "Catharine.Alejoa@btst.com",
    "poste": "Dev"
  },
  {
    "id": 186,
    "nom": "Deloria",
    "prenom": "Yusuk",
    "email": "Deloria.Yusuk@btst.com",
    "poste": "Lead Dev"
  },
  {
    "id": 187,
    "nom": "Leontine",
    "prenom": "Slifka",
    "email": "Leontine.Slifka@btst.com",
    "poste": "Alternant"
  },
  {
    "id": 188,
    "nom": "Wynne",
    "prenom": "Caitlin",
    "email": "Wynne.Caitlin@btst.com",
    "poste": "Dev"
  },
  {
    "id": 189,
    "nom": "Doralynne",
    "prenom": "Sothena",
    "email": "Doralynne.Sothena@btst.com",
    "poste": "Dev"
  },
  {
    "id": 190,
    "nom": "Deloria",
    "prenom": "Bakerman",
    "email": "Deloria.Bakerman@btst.com",
    "poste": "Lead Dev"
  },
  {
    "id": 191,
    "nom": "Basia",
    "prenom": "Gwenore",
    "email": "Basia.Gwenore@btst.com",
    "poste": "Alternant"
  },
  {
    "id": 192,
    "nom": "Elmira",
    "prenom": "Kinnard",
    "email": "Elmira.Kinnard@btst.com",
    "poste": "Lead Dev"
  },
  {
    "id": 193,
    "nom": "Berta",
    "prenom": "Glenden",
    "email": "Berta.Glenden@btst.com",
    "poste": "Lead Dev"
  },
  {
    "id": 194,
    "nom": "Devina",
    "prenom": "Isidore",
    "email": "Devina.Isidore@btst.com",
    "poste": "Alternant"
  },
  {
    "id": 195,
    "nom": "Yolane",
    "prenom": "Sekofski",
    "email": "Yolane.Sekofski@btst.com",
    "poste": "Dev"
  },
  {
    "id": 196,
    "nom": "Cacilie",
    "prenom": "Vilma",
    "email": "Cacilie.Vilma@btst.com",
    "poste": "Manager"
  },
  {
    "id": 197,
    "nom": "Ebonee",
    "prenom": "Erminia",
    "email": "Ebonee.Erminia@btst.com",
    "poste": "Lead Dev"
  },
  {
    "id": 198,
    "nom": "Coral",
    "prenom": "Oster",
    "email": "Coral.Oster@btst.com",
    "poste": "Manager"
  },
  {
    "id": 199,
    "nom": "Raf",
    "prenom": "Leonard",
    "email": "Raf.Leonard@btst.com",
    "poste": "Dev"
  }
]